// class version 50.0 (50)
// access flags 0x31
public final class com/example/stater/MainActivity extends androidx/appcompat/app/AppCompatActivity {

  // compiled from: MainActivity.kt

  @Lkotlin/Metadata;(mv={1, 1, 15}, bv={1, 0, 3}, k=1, d1={"\u0000\u0018\n\u0002\u0018\u0002\n\u0002\u0018\u0002\n\u0002\u0008\u0002\n\u0002\u0010\u0002\n\u0000\n\u0002\u0018\u0002\n\u0000\u0018\u00002\u00020\u0001B\u0005\u00a2\u0006\u0002\u0010\u0002J\u0012\u0010\u0003\u001a\u00020\u00042\u0008\u0010\u0005\u001a\u0004\u0018\u00010\u0006H\u0014\u00a8\u0006\u0007"}, d2={"Lcom/example/stater/MainActivity;", "Landroidx/appcompat/app/AppCompatActivity;", "()V", "onCreate", "", "savedInstanceState", "Landroid/os/Bundle;", "app_debug"})

  // access flags 0x2
  private Ljava/util/HashMap; _$_findViewCache

  // access flags 0x4
  protected onCreate(Landroid/os/Bundle;)V
    // annotable parameter count: 1 (invisible)
    @Lorg/jetbrains/annotations/Nullable;() // invisible, parameter 0
   L0
    LINENUMBER 10 L0
    ALOAD 0
    ALOAD 1
    LDC " before method exec"
    LDC " [ASM] method in androidx/appcompat/app/AppCompatActivity ,name=onCreate"
    INVOKESTATIC android/util/Log.i (Ljava/lang/String;Ljava/lang/String;)I
    POP
    INVOKESPECIAL androidx/appcompat/app/AppCompatActivity.onCreate (Landroid/os/Bundle;)V
    LDC " after method exec"
    LDC " method in androidx/appcompat/app/AppCompatActivity ,name=onCreate"
    INVOKESTATIC android/util/Log.i (Ljava/lang/String;Ljava/lang/String;)I
    POP
   L1
    LINENUMBER 11 L1
    ALOAD 0
    LDC 2131361820
    LDC " before method exec"
    LDC " [ASM] method in com/example/stater/MainActivity ,name=setContentView"
    INVOKESTATIC android/util/Log.i (Ljava/lang/String;Ljava/lang/String;)I
    POP
    INVOKEVIRTUAL com/example/stater/MainActivity.setContentView (I)V
    LDC " after method exec"
    LDC " method in com/example/stater/MainActivity ,name=setContentView"
    INVOKESTATIC android/util/Log.i (Ljava/lang/String;Ljava/lang/String;)I
    POP
   L2
    LINENUMBER 12 L2
    RETURN
   L3
    LOCALVARIABLE this Lcom/example/stater/MainActivity; L0 L3 0
    LOCALVARIABLE savedInstanceState Landroid/os/Bundle; L0 L3 1
    MAXSTACK = 2
    MAXLOCALS = 2

  // access flags 0x1
  public <init>()V
   L0
    LINENUMBER 7 L0
    ALOAD 0
   L1
    LINENUMBER 7 L1
    LDC " before method exec"
    LDC " [ASM] method in androidx/appcompat/app/AppCompatActivity ,name=<init>"
    INVOKESTATIC android/util/Log.i (Ljava/lang/String;Ljava/lang/String;)I
    POP
    INVOKESPECIAL androidx/appcompat/app/AppCompatActivity.<init> ()V
    LDC " after method exec"
    LDC " method in androidx/appcompat/app/AppCompatActivity ,name=<init>"
    INVOKESTATIC android/util/Log.i (Ljava/lang/String;Ljava/lang/String;)I
    POP
    RETURN
   L2
    LOCALVARIABLE this Lcom/example/stater/MainActivity; L0 L2 0
    MAXSTACK = 1
    MAXLOCALS = 1

  // access flags 0x1
  public _$_findCachedViewById(I)Landroid/view/View;
    ALOAD 0
    GETFIELD com/example/stater/MainActivity._$_findViewCache : Ljava/util/HashMap;
    IFNONNULL L0
    ALOAD 0
    NEW java/util/HashMap
    DUP
    LDC " before method exec"
    LDC " [ASM] method in java/util/HashMap ,name=<init>"
    INVOKESTATIC android/util/Log.i (Ljava/lang/String;Ljava/lang/String;)I
    POP
    INVOKESPECIAL java/util/HashMap.<init> ()V
    LDC " after method exec"
    LDC " method in java/util/HashMap ,name=<init>"
    INVOKESTATIC android/util/Log.i (Ljava/lang/String;Ljava/lang/String;)I
    POP
    PUTFIELD com/example/stater/MainActivity._$_findViewCache : Ljava/util/HashMap;
   L0
   FRAME FULL [com/example/stater/MainActivity I] []
    ALOAD 0
    GETFIELD com/example/stater/MainActivity._$_findViewCache : Ljava/util/HashMap;
    ILOAD 1
    LDC " before method exec"
    LDC " [ASM] method in java/lang/Integer ,name=valueOf"
    INVOKESTATIC android/util/Log.i (Ljava/lang/String;Ljava/lang/String;)I
    POP
    INVOKESTATIC java/lang/Integer.valueOf (I)Ljava/lang/Integer;
    LDC " after method exec"
    LDC " method in java/lang/Integer ,name=valueOf"
    INVOKESTATIC android/util/Log.i (Ljava/lang/String;Ljava/lang/String;)I
    POP
    LDC " before method exec"
    LDC " [ASM] method in java/util/HashMap ,name=get"
    INVOKESTATIC android/util/Log.i (Ljava/lang/String;Ljava/lang/String;)I
    POP
    INVOKEVIRTUAL java/util/HashMap.get (Ljava/lang/Object;)Ljava/lang/Object;
    LDC " after method exec"
    LDC " method in java/util/HashMap ,name=get"
    INVOKESTATIC android/util/Log.i (Ljava/lang/String;Ljava/lang/String;)I
    POP
    CHECKCAST android/view/View
    ASTORE 2
    ALOAD 2
    IFNONNULL L1
    ALOAD 0
    ILOAD 1
    LDC " before method exec"
    LDC " [ASM] method in androidx/fragment/app/FragmentActivity ,name=findViewById"
    INVOKESTATIC android/util/Log.i (Ljava/lang/String;Ljava/lang/String;)I
    POP
    INVOKEVIRTUAL androidx/fragment/app/FragmentActivity.findViewById (I)Landroid/view/View;
    LDC " after method exec"
    LDC " method in androidx/fragment/app/FragmentActivity ,name=findViewById"
    INVOKESTATIC android/util/Log.i (Ljava/lang/String;Ljava/lang/String;)I
    POP
    ASTORE 2
    ALOAD 0
    GETFIELD com/example/stater/MainActivity._$_findViewCache : Ljava/util/HashMap;
    ILOAD 1
    LDC " before method exec"
    LDC " [ASM] method in java/lang/Integer ,name=valueOf"
    INVOKESTATIC android/util/Log.i (Ljava/lang/String;Ljava/lang/String;)I
    POP
    INVOKESTATIC java/lang/Integer.valueOf (I)Ljava/lang/Integer;
    LDC " after method exec"
    LDC " method in java/lang/Integer ,name=valueOf"
    INVOKESTATIC android/util/Log.i (Ljava/lang/String;Ljava/lang/String;)I
    POP
    ALOAD 2
    LDC " before method exec"
    LDC " [ASM] method in java/util/HashMap ,name=put"
    INVOKESTATIC android/util/Log.i (Ljava/lang/String;Ljava/lang/String;)I
    POP
    INVOKEVIRTUAL java/util/HashMap.put (Ljava/lang/Object;Ljava/lang/Object;)Ljava/lang/Object;
    LDC " after method exec"
    LDC " method in java/util/HashMap ,name=put"
    INVOKESTATIC android/util/Log.i (Ljava/lang/String;Ljava/lang/String;)I
    POP
    POP
   L1
   FRAME FULL [com/example/stater/MainActivity I android/view/View] []
    ALOAD 2
    ARETURN
    MAXSTACK = 3
    MAXLOCALS = 3

  // access flags 0x1
  public _$_clearFindViewByIdCache()V
    ALOAD 0
    GETFIELD com/example/stater/MainActivity._$_findViewCache : Ljava/util/HashMap;
    IFNULL L0
    ALOAD 0
    GETFIELD com/example/stater/MainActivity._$_findViewCache : Ljava/util/HashMap;
    LDC " before method exec"
    LDC " [ASM] method in java/util/HashMap ,name=clear"
    INVOKESTATIC android/util/Log.i (Ljava/lang/String;Ljava/lang/String;)I
    POP
    INVOKEVIRTUAL java/util/HashMap.clear ()V
    LDC " after method exec"
    LDC " method in java/util/HashMap ,name=clear"
    INVOKESTATIC android/util/Log.i (Ljava/lang/String;Ljava/lang/String;)I
    POP
   L0
   FRAME FULL [com/example/stater/MainActivity] []
    RETURN
    MAXSTACK = 1
    MAXLOCALS = 1
}
